<Properties StartupConfiguration="Multiple Projects">
  <MonoDevelop.Ide.Workbench ActiveDocument="FIL.Configuration.Api/Utilities/DataSettings.cs">
    <Files>
      <File FileName="FIL.Api/QueryHandlers/TransactionReport/TransactionReportQueryHandler.cs" Line="16" Column="1" />
      <File FileName="FIL.Api/Repositories/ReportingRepository.cs" Line="20" Column="1" />
      <File FileName="FIL.Web.Admin/Controllers/Reporting/FeelUserReportController.cs" Line="15" Column="42" />
      <File FileName="FIL.Web.Admin/Modules/AutofacModule.cs" Line="17" Column="80" />
      <File FileName="FIL.Api/Utilities/DataSettings.cs" Line="10" Column="6" />
      <File FileName="FIL.Api.Core/Utilities/IDataSettings.cs" Line="3" Column="14" />
      <File FileName="FIL.Configuration.Api/Utilities/DataSettings.cs" Line="2" Column="10" />
    </Files>
    <Pads>
      <Pad Id="ProjectPad">
        <State name="__root__">
          <Node name="FIL" expanded="True">
            <Node name="FIL.Api" expanded="True">
              <Node name="Utilities" expanded="True" />
            </Node>
            <Node name="FIL.Api.Core" expanded="True">
              <Node name="Utilities" expanded="True" />
            </Node>
            <Node name="FIL.Configuration.Api" expanded="True">
              <Node name="Utilities" expanded="True">
                <Node name="DataSettings.cs" selected="True" />
              </Node>
            </Node>
            <Node name="FIL.Contracts" expanded="True">
              <Node name="Queries" expanded="True">
                <Node name="Reporting" expanded="True" />
              </Node>
            </Node>
            <Node name="FIL.Web.Admin" expanded="True">
              <Node name="Controllers" expanded="True">
                <Node name="Reporting" expanded="True" />
              </Node>
              <Node name="Modules" expanded="True" />
            </Node>
          </Node>
        </State>
      </Pad>
    </Pads>
  </MonoDevelop.Ide.Workbench>
  <MonoDevelop.Ide.ItemProperties.FIL.Configuration.Api PreferredExecutionTarget="/Applications/Google Chrome.app" />
  <MonoDevelop.Ide.ItemProperties.FIL.Web PreferredExecutionTarget="/Applications/Google Chrome.app" />
  <MonoDevelop.Ide.ItemProperties.FIL.Web.Admin PreferredExecutionTarget="/Applications/Google Chrome.app" />
  <MonoDevelop.Ide.DebuggingService.PinnedWatches />
  <DisabledProjects>
    <String>FIL.Window.Service/FIL.Window.Service.csproj</String>
  </DisabledProjects>
  <MonoDevelop.Ide.Workspace ActiveConfiguration="Debug" />
  <MonoDevelop.Ide.DebuggingService.Breakpoints>
    <BreakpointStore />
  </MonoDevelop.Ide.DebuggingService.Breakpoints>
  <MultiItemStartupConfigurations>
    <MultiItemSolutionRunConfiguration Id="Multiple Projects" Name="Multiple Projects">
      <Items>
        <StartupItem ItemId="{6CEA710B-7F38-40D6-BD32-5277B46FAD35}" ItemName="FIL.Api" />
        <StartupItem ItemId="{767A18D8-C584-41D6-AC46-76BE6D0AC0B7}" ItemName="FIL.Configuration.Api" ConfigurationId="Kz.Configuration.Api" />
        <StartupItem ItemId="{74FC6647-1218-4BD4-89A8-9EEFA4384E53}" ItemName="FIL.Web" />
        <StartupItem ItemId="{02D8D788-8EA6-410A-B08B-AA85C8E51D54}" ItemName="FIL.Web.Admin" ConfigurationId="Default" />
      </Items>
    </MultiItemSolutionRunConfiguration>
  </MultiItemStartupConfigurations>
  <MonoDevelop.Ide.ItemProperties.FIL.Api PreferredExecutionTarget="/Applications/Google Chrome.app" />
</Properties>